nr_documents_records_model_builder/__init__.py
nr_documents_records_model_builder/version.py
nr_documents_records_model_builder/models/__init__.py
nr_documents_records_model_builder/models/nr-documents-records-model.yaml
nr_documents_records_model_builder/models/nr-documents-records.yaml
nr_documents_records_model_builder-1.0.0.dist-info/METADATA
nr_documents_records_model_builder-1.0.0.dist-info/WHEEL
nr_documents_records_model_builder-1.0.0.dist-info/entry_points.txt
nr_documents_records_model_builder-1.0.0.dist-info/top_level.txt
nr_documents_records_model_builder-1.0.0.dist-info/RECORD
