Metadata-Version: 2.1
Name: nr-documents-records-model-builder
Version: 1.0.0
Summary: OARepo model builder extension for NR document records
Home-page: https://github.com/NarodniRepozitar/nr-documents-records
Author: CESNET
Author-email: bauer@cesnet.cz
License: MIT
Keywords: National Repository documents model builder plugin Invenio
Platform: any
Classifier: Development Status :: 5 - Production/Stable
Requires-Python: >=3.9
Requires-Dist: oarepo-model-builder (>=1.0.0dev9)
Requires-Dist: oarepo-model-builder-multilingual (>=0.1.9)
Requires-Dist: oarepo-model-builder-ui (>=1.0.0)
Requires-Dist: nr-vocabularies (>=0.0.1)
Requires-Dist: nr-vocabularies-model-builder (>=0.0.2)
Requires-Dist: oarepo-vocabularies-model-builder (>=0.0.6)
Requires-Dist: nr-common-metadata-model-builder (>=4.0.0.dev5)
